odoo/addons/account_invoice_start_end_dates/README.rst
odoo/addons/account_invoice_start_end_dates/__init__.py
odoo/addons/account_invoice_start_end_dates/__manifest__.py
odoo/addons/account_invoice_start_end_dates/demo/product_demo.xml
odoo/addons/account_invoice_start_end_dates/i18n/account_invoice_start_end_dates.pot
odoo/addons/account_invoice_start_end_dates/i18n/fr.po
odoo/addons/account_invoice_start_end_dates/i18n/fr_FR.po
odoo/addons/account_invoice_start_end_dates/i18n/hr.po
odoo/addons/account_invoice_start_end_dates/i18n/hr_HR.po
odoo/addons/account_invoice_start_end_dates/i18n/it.po
odoo/addons/account_invoice_start_end_dates/i18n/nl_NL.po
odoo/addons/account_invoice_start_end_dates/i18n/pt.po
odoo/addons/account_invoice_start_end_dates/models/__init__.py
odoo/addons/account_invoice_start_end_dates/models/account_move.py
odoo/addons/account_invoice_start_end_dates/models/account_move_line.py
odoo/addons/account_invoice_start_end_dates/models/product_template.py
odoo/addons/account_invoice_start_end_dates/readme/CONTRIBUTORS.rst
odoo/addons/account_invoice_start_end_dates/readme/DESCRIPTION.rst
odoo/addons/account_invoice_start_end_dates/static/description/icon.png
odoo/addons/account_invoice_start_end_dates/static/description/index.html
odoo/addons/account_invoice_start_end_dates/tests/__init__.py
odoo/addons/account_invoice_start_end_dates/tests/test_invoice_start_end_dates.py
odoo/addons/account_invoice_start_end_dates/views/account_move.xml
odoo/addons/account_invoice_start_end_dates/views/account_move_line.xml
odoo/addons/account_invoice_start_end_dates/views/product_template.xml
odoo14_addon_account_invoice_start_end_dates-14.0.1.2.0.dist-info/METADATA
odoo14_addon_account_invoice_start_end_dates-14.0.1.2.0.dist-info/WHEEL
odoo14_addon_account_invoice_start_end_dates-14.0.1.2.0.dist-info/top_level.txt
odoo14_addon_account_invoice_start_end_dates-14.0.1.2.0.dist-info/RECORD
